dtfilter
