Metadata-Version: 1.1
Name: dtfilter
Version: 0.0.2
Summary: Library for data filtering and analysis
Home-page: UNKNOWN
Author: Deepak Kamath
Author-email: dkamath1998@gmail.com
License: MIT
Keywords: dataanalysis
Platform: UNKNOWN
Classifier: Development Status :: 5 - Production/Stable
Classifier: Intended Audience :: Education
Classifier: Operating System :: Microsoft :: Windows :: Windows 10
Classifier: License :: OSI Approved :: MIT License
Classifier: Programming Language :: Python :: 3
